closedmindedness.py
closedmindedness-1.3.dist-info/METADATA
closedmindedness-1.3.dist-info/WHEEL
closedmindedness-1.3.dist-info/top_level.txt
closedmindedness-1.3.dist-info/RECORD
